bilayer_letb/__init__.py
bilayer_letb/api.py
bilayer_letb/functions.py
bilayer_letb/helper.py
bilayer_letb/model.py
bilayer_letb/descriptors/__init__.py
bilayer_letb/descriptors/descriptors_interlayer.py
bilayer_letb/descriptors/descriptors_intralayer.py
bilayer_letb/parameters/fit_interlayer.hdf5
bilayer_letb/parameters/fit_intralayer.hdf5
bilayer_letb-0.0.2.dist-info/METADATA
bilayer_letb-0.0.2.dist-info/WHEEL
bilayer_letb-0.0.2.dist-info/top_level.txt
bilayer_letb-0.0.2.dist-info/RECORD
